[
  {
    "id": "1ef09912-857c-4e15-9bba-615d71fe6f74",
    "data": [
      {
        "text": "Right",
        "userDefined": false
      }
    ],
    "isTemplate": false,
    "count": 0,
    "lang": "en",
    "updated": 0
  },
  {
    "id": "8aa187bc-8c7a-45c6-b743-5733e5bb79c0",
    "data": [
      {
        "text": "Yes correct",
        "userDefined": false
      }
    ],
    "isTemplate": false,
    "count": 0,
    "lang": "en",
    "updated": 0
  },
  {
    "id": "11c82900-7473-4250-a02c-92ff36863e30",
    "data": [
      {
        "text": "Yes that is my name",
        "userDefined": false
      }
    ],
    "isTemplate": false,
    "count": 0,
    "lang": "en",
    "updated": 0
  },
  {
    "id": "baf7f0bd-2b6c-4b0c-a44f-1ae858794b41",
    "data": [
      {
        "text": "Yes",
        "userDefined": false
      }
    ],
    "isTemplate": false,
    "count": 0,
    "lang": "en",
    "updated": 0
  }
]